{
  "restaurantList": [
    {
      "address": "50 Dang Thi Nhu Street Nguyen Thai Binh Ward, District 1, Ho Chi Minh City 700000 Vietnam",
      "phone": "+84 96 153 95 00",
      "website": "http://www.facebook.com/winkingseal",
      "open_time": "3:00 PM - 12:00 AM",
      "details": {
        "price_range": "₫795,454,528 - ₫2,147,483,647",
        "cuisines": "Brew Pub, Bar, Pub",
        "special_diets": "Vegetarian Friendly"
      },
      "name": "Winking Seal Beer Co.",
      "images": [
        "https://media-cdn.tripadvisor.com/media/photo-o/14/b5/46/b2/we-have-16-taps-serving.jpg",
        "https://media-cdn.tripadvisor.com/media/photo-o/14/b5/54/37/enjoy-delicious-deserts.jpg",
        "https://media-cdn.tripadvisor.com/media/photo-o/14/b5/46/9b/two-nitro-taps-at-each.jpg",
        "https://media-cdn.tripadvisor.com/media/photo-o/14/b5/55/99/fresh-organic-ingredients.jpg",
        "https://media-cdn.tripadvisor.com/media/photo-o/0e/67/98/38/fried-mac-and-cheese.jpg",
        "https://media-cdn.tripadvisor.com/media/photo-o/14/b5/46/cb/our-premium-micro-matic.jpg",
        "https://media-cdn.tripadvisor.com/media/photo-o/14/b5/46/aa/communal-seating-on-our.jpg",
        "https://media-cdn.tripadvisor.com/media/photo-o/14/b5/46/97/our-main-bar-featuring.jpg",
        "https://media-cdn.tripadvisor.com/media/photo-o/14/b5/46/d0/ask-your-bartenders-about.jpg",
        "https://media-cdn.tripadvisor.com/media/photo-o/14/b5/46/93/art-deco-design-through.jpg",
        "https://media-cdn.tripadvisor.com/media/photo-o/14/b5/46/b2/we-have-16-taps-serving.jpg",
        "https://media-cdn.tripadvisor.com/media/photo-o/14/b5/54/37/enjoy-delicious-deserts.jpg",
        "https://media-cdn.tripadvisor.com/media/photo-o/14/b5/46/9b/two-nitro-taps-at-each.jpg",
        "https://media-cdn.tripadvisor.com/media/photo-o/14/b5/55/99/fresh-organic-ingredients.jpg",
        "https://media-cdn.tripadvisor.com/media/photo-o/0e/67/98/38/fried-mac-and-cheese.jpg",
        "https://media-cdn.tripadvisor.com/media/photo-o/14/b5/46/cb/our-premium-micro-matic.jpg",
        "https://media-cdn.tripadvisor.com/media/photo-o/14/b5/46/aa/communal-seating-on-our.jpg",
        "https://media-cdn.tripadvisor.com/media/photo-o/14/b5/46/97/our-main-bar-featuring.jpg",
        "https://media-cdn.tripadvisor.com/media/photo-o/14/b5/46/d0/ask-your-bartenders-about.jpg",
        "https://media-cdn.tripadvisor.com/media/photo-o/14/b5/46/93/art-deco-design-through.jpg"
      ]
    }
  ],
  "attractionList": [
    {
      "about": "All you need to step foot in the door.",
      "suggested_duration": "2-3 hours",
      "admission_ticket": "from $16.51",
      "images": [
        "https://media-cdn.tripadvisor.com/media/photo-o/1b/2a/05/1c/photo8jpg.jpg",
        "https://media-cdn.tripadvisor.com/media/photo-o/04/85/62/6b/cu-chi-tunnel-tour-private.jpg",
        "https://media-cdn.tripadvisor.com/media/photo-o/1b/72/f3/0e/cu-chi-tunnels.jpg",
        "https://media-cdn.tripadvisor.com/media/photo-o/1b/72/f3/0c/cu-chi-tunnels.jpg",
        "https://media-cdn.tripadvisor.com/media/photo-o/1b/72/f3/09/cu-chi-tunnels.jpg",
        "https://media-cdn.tripadvisor.com/media/photo-o/1b/72/f3/06/cu-chi-tunnels.jpg",
        "https://media-cdn.tripadvisor.com/media/photo-o/1b/72/f3/01/cu-chi-tunnels.jpg",
        "https://media-cdn.tripadvisor.com/media/photo-o/1b/72/f2/ff/cu-chi-tunnels.jpg",
        "https://media-cdn.tripadvisor.com/media/photo-o/1b/72/f2/fc/cu-chi-tunnels.jpg",
        "https://media-cdn.tripadvisor.com/media/photo-o/1b/72/f2/f9/cu-chi-tunnels.jpg"
      ],
      "address": "Phu Hiep TL15 Phu Hiep, Ho Chi Minh City 700000 Vietnam",
      "open_time": "7:00 AM - 6:00 PM",
      "name": "Cu Chi Tunnels"
    }
  ],
  "hotelList": [
    {
      "name": "LOTTE HOTEL SAIGON",
      "address": "2A - 4A Ton Duc Thang St, District 1, Ho Chi Minh City 70000 Vietnam",
      "phone": "",
      "email": "",
      "about": "Fronting the scenic Saigon River and only 3-5 minute walk to famous Opera House, Dong Khoi Street and Le Thanh Ton Street for shopping, dining and entertainment, LOTTE HOTEL SAIGON, the most beloved 5-star hotel in Ho Chi Minh City, combines natural beauty and sheer opulence to provide the best for the discerning traveler. The breathtaking resort-setting and its distinctive architectural interior gives a feeling of luxury and tranquility. A legendary hotel inherits good and ancient Vietnam with garden falls, pond and fountain. The top pattern of the bronze drum, symbol of the sun, from ancient times, frames the entrance of guest rooms. The twelve horary signs in the atrium, the lobby surrounded by colonnades and the giant horse sculptures all of which induce you to meander in the space of the hotel.",
      "amenities": {
        "room_features": [
          "Air conditioning",
          "Housekeeping",
          "Interconnected rooms available",
          "Room service",
          "Safe",
          "Minibar",
          "Refrigerator",
          "Flatscreen TV"
        ],
        "room_types": [
          "Non-smoking rooms",
          "Suites",
          "Family rooms",
          "Smoking rooms available"
        ],
        "property_amenities": [
          "Valet parking",
          "Free High Speed Internet (WiFi)",
          "Pool",
          "Fitness Center with Gym / Workout Room",
          "Bar / lounge",
          "Airport transportation",
          "Business Center with Internet Access",
          "Conference facilities"
        ]
      },
      "images": [
        "https://media-cdn.tripadvisor.com/media/photo-o/07/45/10/5e/executive-twin-bed-room--v5339256.jpg",
        "https://media-cdn.tripadvisor.com/media/photo-o/07/45/0f/ea/deluxe-suite-king-bed-room--v5339.jpg",
        "https://media-cdn.tripadvisor.com/media/photo-o/07/45/0f/f9/deluxe-suite-king-bed-room--v5339.jpg",
        "https://media-cdn.tripadvisor.com/media/photo-o/07/45/10/1d/deluxe-twin-bed-room--v5339425.jpg",
        "https://media-cdn.tripadvisor.com/media/photo-o/07/45/10/99/presidential-suite--v5339221.jpg",
        "https://media-cdn.tripadvisor.com/media/photo-o/07/45/0f/fd/deluxe-suite-king-bed-room--v5339.jpg",
        "https://media-cdn.tripadvisor.com/media/photo-o/07/45/10/5c/executive-twin-bed-room--v5339279.jpg"
      ]
    }
  ]
}
